l2data_reader/__init__.py
l2data_reader/enums.py
l2data_reader/exceptions.py
l2data_reader/mmap_utils.py
l2data_reader/models.py
l2data_reader/reader.py
l2data_reader/utils.py
l2data_reader/writer.py
l2data_reader/proto/__init__.py
l2data_reader/proto/market_data_pb2.py
l2data_reader-0.1.18.dist-info/licenses/LICENSE
l2data_reader-0.1.18.dist-info/METADATA
l2data_reader-0.1.18.dist-info/WHEEL
l2data_reader-0.1.18.dist-info/top_level.txt
l2data_reader-0.1.18.dist-info/RECORD
