Metadata-Version: 2.4
Name: l2data-reader
Version: 0.1.18
Summary: A package for reading Level 2 market data
Author-email: JasonJiang0303 <chinese88+0303@2925.com>
License-Expression: MIT
Project-URL: Homepage, https://github.com/JasonJiang0303/l2data-reader
Project-URL: Bug Tracker, https://github.com/JasonJiang0303/l2data-reader/issues
Classifier: Programming Language :: Python :: 3
Classifier: Operating System :: OS Independent
Requires-Python: >=3.7
License-File: LICENSE
Requires-Dist: protobuf>=3.12.0
Dynamic: license-file
